emoji_list_discord/Activities.py
emoji_list_discord/Animals_and_nature.py
emoji_list_discord/Food_and_drink.py
emoji_list_discord/Objects.py
emoji_list_discord/Smileys_and_people.py
emoji_list_discord/Symbols.py
emoji_list_discord/Travel_and_places.py
emoji_list_discord/__init__.py
emoji_list_discord-0.1.1.dist-info/LICENSE
emoji_list_discord-0.1.1.dist-info/METADATA
emoji_list_discord-0.1.1.dist-info/WHEEL
emoji_list_discord-0.1.1.dist-info/top_level.txt
emoji_list_discord-0.1.1.dist-info/RECORD
