Metadata-Version: 2.1
Name: emoji_list_discord
Version: 0.1.1
Summary: List of emojis that can be used on Discord
Home-page: https://github.com/Project-Rain/emoji_list_discord
Author: 8ka1alu
Author-email: 8ka1alu@gmail.com
Keywords: emoji list discord
License-File: LICENSE
